LICENSE
README.md
setup.py
exodia/__init__.py
exodia/bases.py
exodia/exceptions.py
exodia/fields.py
exodia/utils.py
exodia/validators.py
exodia.egg-info/PKG-INFO
exodia.egg-info/SOURCES.txt
exodia.egg-info/dependency_links.txt
exodia.egg-info/top_level.txt
tests/test_instance_creation.py
tests/test_validation.py