Metadata-Version: 2.1
Name: exodia
Version: 1.0.6
Summary: A client library for validation without hassle
Home-page: https://github.com/LeOndaz/exodia
Author: LeOndaz
Author-email: ahmeddark369@gmail.com
License-File: LICENSE
